cmn_ai/__init__.py
cmn_ai/activations.py
cmn_ai/learner.py
cmn_ai/losses.py
cmn_ai/plot.py
cmn_ai/callbacks/__init__.py
cmn_ai/callbacks/core.py
cmn_ai/callbacks/hook.py
cmn_ai/callbacks/schedule.py
cmn_ai/callbacks/training.py
cmn_ai/tabular/__init__.py
cmn_ai/tabular/data.py
cmn_ai/tabular/eda.py
cmn_ai/tabular/preprocessing.py
cmn_ai/text/__init__.py
cmn_ai/text/data.py
cmn_ai/utils/__init__.py
cmn_ai/utils/data.py
cmn_ai/utils/processors.py
cmn_ai/utils/utils.py
cmn_ai/vision/__init__.py
cmn_ai/vision/core.py
cmn_ai/vision/data.py
cmn_ai-0.1.0.dist-info/METADATA
cmn_ai-0.1.0.dist-info/WHEEL
cmn_ai-0.1.0.dist-info/licenses/LICENSE
cmn_ai-0.1.0.dist-info/RECORD
