Metadata-Version: 2.4
Name: cmn-ai
Version: 0.1.0
Summary: A comprehensive machine learning library with utilities for vision, text, and tabular data
Author-email: ImadDabbura <imad.dabbura@hotmail.com>
License: MIT
License-File: LICENSE
Keywords: deep-learning,machine-learning,tabular,text,vision
Classifier: Development Status :: 3 - Alpha
Classifier: Intended Audience :: Developers
Classifier: Intended Audience :: Science/Research
Classifier: License :: OSI Approved :: MIT License
Classifier: Programming Language :: Python :: 3
Classifier: Programming Language :: Python :: 3.13
Classifier: Topic :: Scientific/Engineering :: Artificial Intelligence
Classifier: Topic :: Software Development :: Libraries :: Python Modules
Requires-Python: >=3.13
Requires-Dist: datasets<4.0.0,>=3.3.2
Requires-Dist: fastcore<2.0.0,>=1.7.29
Requires-Dist: fastprogress<2.0.0,>=1.0.3
Requires-Dist: matplotlib<4.0.0,>=3.10.1
Requires-Dist: numpy<3.0.0,>=2.2.3
Requires-Dist: pandas<3.0.0,>=2.2.0
Requires-Dist: pyarrow-hotfix<0.7,>=0.6
Requires-Dist: scikit-learn<2.0.0,>=1.6.1
Requires-Dist: scipy<2.0.0,>=1.15.2
Requires-Dist: seaborn>=0.13.0
Requires-Dist: torch<3.0.0,>=2.6.0
Requires-Dist: torcheval<0.1.0,>=0.0.7
Requires-Dist: torchinfo<2.0.0,>=1.8.0
Requires-Dist: torchvision<0.22.0,>=0.21.0
Provides-Extra: dev
Requires-Dist: black>=23.1.0; extra == 'dev'
Requires-Dist: flake8>=6.0.0; extra == 'dev'
Requires-Dist: isort>=5.12.0; extra == 'dev'
Requires-Dist: pre-commit>=3.1.1; extra == 'dev'
Requires-Dist: pytest-cov>=4.0.0; extra == 'dev'
Requires-Dist: pytest>=7.2.1; extra == 'dev'
Provides-Extra: docs
Requires-Dist: mkdocs-material>=9.1.12; extra == 'docs'
Requires-Dist: mkdocs>=1.4.3; extra == 'docs'
Requires-Dist: mkdocstrings-python>=1.0.0; extra == 'docs'
